{
  "appInfo" : {
    "build" : "233.14015.106",
    "buildDate" : "2024-01-25T05:01:00Z[UTC]",
    "productCode" : "IC",
    "generated" : "2024-02-21T03:48:23.434338457Z",
    "os" : "Linux 6.5.0-18-generic",
    "runtime" : "JetBrains s.r.o. 17.0.9 17.0.9+7-b1087.11"
  },
  "runtimeInfo" : {
    "maxMemory" : 2147483648,
    "numberOfProcessors" : 8,
    "maxNumberOfIndexingThreads" : 7,
    "maxSizeOfFileForIntelliSense" : 2560000,
    "maxSizeOfFileForContentLoading" : 20971520
  },
  "type" : "Scanning",
  "projectIndexingActivityHistory" : {
    "projectName" : "Function",
    "times" : {
      "scanningReason" : "On project open",
      "scanningType" : "FULL_ON_PROJECT_OPEN",
      "scanningId" : 2,
      "creatingIteratorsTime" : 1667657,
      "concurrentHandlingWallTimeWithoutPauses" : 99739706,
      "concurrentHandlingWallTimeWithPauses" : 99739706,
      "concurrentHandlingSumOfThreadTimesWithPauses" : 117641415,
      "concurrentIterationAndScannersApplicationSumOfThreadTimesWithPauses" : 73993506,
      "concurrentFileCheckSumOfThreadTimesWithPauses" : 42395284,
      "delayedPushPropertiesStageTime" : 8065,
      "indexExtensionsTime" : 380797,
      "dumbWallTimeWithPauses" : 0,
      "dumbWallTimeWithoutPauses" : 0,
      "updatingStart" : "2024-02-21T03:48:23.3110148Z",
      "updatingEnd" : "2024-02-21T03:48:23.433513701Z",
      "totalWallTimeWithPauses" : 122468283,
      "wallTimeOnPause" : 0,
      "wasInterrupted" : false,
      "totalWallTimeWithoutPauses" : 122468283
    },
    "fileCount" : {
      "numberOfFileProviders" : 9,
      "numberOfScannedFiles" : 28808,
      "numberOfFilesIndexedByInfrastructureExtensionsDuringScan" : 0,
      "numberOfFilesScheduledForIndexingAfterScan" : 1
    },
    "scanningStatistics" : [ {
      "providerName" : "JDK 18 /usr/lib/jvm/java-1.18.0-openjdk-amd64",
      "numberOfScannedFiles" : 27162,
      "numberOfSkippedFiles" : 0,
      "numberOfFilesForIndexing" : 0,
      "numberOfFilesFullyIndexedByInfrastructureExtensions" : 0,
      "filesFullyIndexedByInfrastructureExtensions" : [ ],
      "statusTime" : 15798153,
      "totalOneThreadTimeWithPauses" : 96842240,
      "iterationAndScannersApplicationTime" : 67869271,
      "filesCheckTime" : 28912785,
      "timeProcessingUpToDateFiles" : 0,
      "timeUpdatingContentLessIndexes" : 0,
      "timeIndexingWithoutContentViaInfrastructureExtension" : 0,
      "roots" : [ ]
    }, {
      "providerName" : "Module 'Function' (all roots)",
      "numberOfScannedFiles" : 12,
      "numberOfSkippedFiles" : 0,
      "numberOfFilesForIndexing" : 1,
      "numberOfFilesFullyIndexedByInfrastructureExtensions" : 0,
      "filesFullyIndexedByInfrastructureExtensions" : [ ],
      "statusTime" : 3278859,
      "totalOneThreadTimeWithPauses" : 10208151,
      "iterationAndScannersApplicationTime" : 1214602,
      "filesCheckTime" : 8001888,
      "timeProcessingUpToDateFiles" : 0,
      "timeUpdatingContentLessIndexes" : 948410,
      "timeIndexingWithoutContentViaInfrastructureExtension" : 380797,
      "roots" : [ ]
    }, {
      "providerName" : "Library KotlinJavaRuntime (#4 class roots, #4 source roots)",
      "numberOfScannedFiles" : 1412,
      "numberOfSkippedFiles" : 0,
      "numberOfFilesForIndexing" : 0,
      "numberOfFilesFullyIndexedByInfrastructureExtensions" : 0,
      "filesFullyIndexedByInfrastructureExtensions" : [ ],
      "statusTime" : 2437725,
      "totalOneThreadTimeWithPauses" : 9373616,
      "iterationAndScannersApplicationTime" : 4327505,
      "filesCheckTime" : 4982722,
      "timeProcessingUpToDateFiles" : 173016,
      "timeUpdatingContentLessIndexes" : 0,
      "timeIndexingWithoutContentViaInfrastructureExtension" : 0,
      "roots" : [ ]
    }, {
      "providerName" : "Indexable set contributor 'com.intellij.javaee.ExternalResourcesRootsProvider@ac181d9' (non-project)",
      "numberOfScannedFiles" : 215,
      "numberOfSkippedFiles" : 4,
      "numberOfFilesForIndexing" : 0,
      "numberOfFilesFullyIndexedByInfrastructureExtensions" : 0,
      "filesFullyIndexedByInfrastructureExtensions" : [ ],
      "statusTime" : 122834,
      "totalOneThreadTimeWithPauses" : 794620,
      "iterationAndScannersApplicationTime" : 533737,
      "filesCheckTime" : 238069,
      "timeProcessingUpToDateFiles" : 0,
      "timeUpdatingContentLessIndexes" : 0,
      "timeIndexingWithoutContentViaInfrastructureExtension" : 0,
      "roots" : [ ]
    }, {
      "providerName" : "Indexable set contributor 'Scratches & Consoles' (project)",
      "numberOfScannedFiles" : 0,
      "numberOfSkippedFiles" : 0,
      "numberOfFilesForIndexing" : 0,
      "numberOfFilesFullyIndexedByInfrastructureExtensions" : 0,
      "filesFullyIndexedByInfrastructureExtensions" : [ ],
      "statusTime" : 0,
      "totalOneThreadTimeWithPauses" : 158229,
      "iterationAndScannersApplicationTime" : 10159,
      "filesCheckTime" : 114927,
      "timeProcessingUpToDateFiles" : 0,
      "timeUpdatingContentLessIndexes" : 0,
      "timeIndexingWithoutContentViaInfrastructureExtension" : 0,
      "roots" : [ ]
    }, {
      "providerName" : "Indexable set contributor 'org.jetbrains.kotlin.idea.base.indices.contributors.BuiltInsIndexableSetContributor@13ff1655' (non-project)",
      "numberOfScannedFiles" : 7,
      "numberOfSkippedFiles" : 0,
      "numberOfFilesForIndexing" : 0,
      "numberOfFilesFullyIndexedByInfrastructureExtensions" : 0,
      "filesFullyIndexedByInfrastructureExtensions" : [ ],
      "statusTime" : 21742,
      "totalOneThreadTimeWithPauses" : 112542,
      "iterationAndScannersApplicationTime" : 20849,
      "filesCheckTime" : 70513,
      "timeProcessingUpToDateFiles" : 0,
      "timeUpdatingContentLessIndexes" : 0,
      "timeIndexingWithoutContentViaInfrastructureExtension" : 0,
      "roots" : [ ]
    }, {
      "providerName" : "Indexable set contributor 'Scratches & Consoles' (non-project)",
      "numberOfScannedFiles" : 0,
      "numberOfSkippedFiles" : 0,
      "numberOfFilesForIndexing" : 0,
      "numberOfFilesFullyIndexedByInfrastructureExtensions" : 0,
      "filesFullyIndexedByInfrastructureExtensions" : [ ],
      "statusTime" : 0,
      "totalOneThreadTimeWithPauses" : 57569,
      "iterationAndScannersApplicationTime" : 7083,
      "filesCheckTime" : 27462,
      "timeProcessingUpToDateFiles" : 0,
      "timeUpdatingContentLessIndexes" : 0,
      "timeIndexingWithoutContentViaInfrastructureExtension" : 0,
      "roots" : [ ]
    }, {
      "providerName" : "Indexable set contributor 'com.intellij.javaee.ExternalResourcesRootsProvider@ac181d9' (project)",
      "numberOfScannedFiles" : 0,
      "numberOfSkippedFiles" : 0,
      "numberOfFilesForIndexing" : 0,
      "numberOfFilesFullyIndexedByInfrastructureExtensions" : 0,
      "filesFullyIndexedByInfrastructureExtensions" : [ ],
      "statusTime" : 0,
      "totalOneThreadTimeWithPauses" : 54723,
      "iterationAndScannersApplicationTime" : 5751,
      "filesCheckTime" : 27121,
      "timeProcessingUpToDateFiles" : 0,
      "timeUpdatingContentLessIndexes" : 0,
      "timeIndexingWithoutContentViaInfrastructureExtension" : 0,
      "roots" : [ ]
    }, {
      "providerName" : "Indexable set contributor 'org.jetbrains.kotlin.idea.base.indices.contributors.BuiltInsIndexableSetContributor@13ff1655' (project)",
      "numberOfScannedFiles" : 0,
      "numberOfSkippedFiles" : 0,
      "numberOfFilesForIndexing" : 0,
      "numberOfFilesFullyIndexedByInfrastructureExtensions" : 0,
      "filesFullyIndexedByInfrastructureExtensions" : [ ],
      "statusTime" : 0,
      "totalOneThreadTimeWithPauses" : 39725,
      "iterationAndScannersApplicationTime" : 4549,
      "filesCheckTime" : 19797,
      "timeProcessingUpToDateFiles" : 0,
      "timeUpdatingContentLessIndexes" : 0,
      "timeIndexingWithoutContentViaInfrastructureExtension" : 0,
      "roots" : [ ]
    } ]
  }
}